bingImageSpiderCreatedByHanXu/Spider.py
bingImageSpiderCreatedByHanXu/__init__.py
bingImageSpiderCreatedByHanXu-0.0.3.dist-info/LICENSE
bingImageSpiderCreatedByHanXu-0.0.3.dist-info/METADATA
bingImageSpiderCreatedByHanXu-0.0.3.dist-info/WHEEL
bingImageSpiderCreatedByHanXu-0.0.3.dist-info/top_level.txt
bingImageSpiderCreatedByHanXu-0.0.3.dist-info/RECORD
